pysrc3.py
pysrc3-0.1.3.dist-info/DESCRIPTION.rst
pysrc3-0.1.3.dist-info/METADATA
pysrc3-0.1.3.dist-info/RECORD
pysrc3-0.1.3.dist-info/WHEEL
pysrc3-0.1.3.dist-info/entry_points.txt
pysrc3-0.1.3.dist-info/metadata.json
pysrc3-0.1.3.dist-info/top_level.txt
