Metadata-Version: 1.1
Name: pysrc3
Version: 0.1.3
Summary: Opens the source file of Python modules in an editor, a pager, or any other program of choice.
Home-page: https://github.com/astralblue/pysrc3
Author: Eugene M. Kim
Author-email: astralblue@gmail.com
License: MIT license
Keywords: pysrc3
Platform: UNKNOWN
Classifier: Development Status :: 2 - Pre-Alpha
Classifier: Intended Audience :: Developers
Classifier: License :: OSI Approved :: MIT License
Classifier: Natural Language :: English
Classifier: Programming Language :: Python :: 3
Classifier: Programming Language :: Python :: 3.4
Classifier: Programming Language :: Python :: 3.5
Classifier: Programming Language :: Python :: 3.6
